DeSlin/__init__.py
DeSlin/modulo.py
DeSlin-0.2.dist-info/METADATA
DeSlin-0.2.dist-info/WHEEL
DeSlin-0.2.dist-info/top_level.txt
DeSlin-0.2.dist-info/RECORD
