Metadata-Version: 2.1
Name: DeSlin
Version: 0.2
Summary: Una librería de ejemplo llamada DeSlin
Home-page: https://github.com/tu_usuario/DeSlin
Author: Tu Nombre
Author-email: abraham.gu1996@gmail.com
Classifier: Programming Language :: Python :: 3
Classifier: License :: OSI Approved :: MIT License
Classifier: Operating System :: OS Independent
Requires-Python: >=3.6
